easy_tools/base/common.py
easy_tools/base/demo/case_convert_demo.py
easy_tools/base/demo/pyhumps_demo.py
easy_tools/base/design_pattern/singleton.py
easy_tools/base/encryption/aes.py
easy_tools/base/encryption/rsa.py
easy_tools/base/encryption/translate.py
easy_tools/base/time_translate/base.py
easy_tools/test.py
py_easy_tools-0.1.4.dist-info/LICENSE
py_easy_tools-0.1.4.dist-info/METADATA
py_easy_tools-0.1.4.dist-info/WHEEL
py_easy_tools-0.1.4.dist-info/RECORD
