Metadata-Version: 2.1
Name: py-easy-tools
Version: 0.1.4
Summary: tools
License: Apache-2.0
Author: pumingzheng
Author-email: pumz_1991@126.com
Requires-Python: >=3.11,<4.0
Classifier: License :: OSI Approved :: Apache Software License
Classifier: Programming Language :: Python :: 3
Classifier: Programming Language :: Python :: 3.11
Provides-Extra: center
Requires-Dist: case-convert (>=1.1.0,<2.0.0)
Requires-Dist: django[centerapi] (>=4.1.7,<5.0.0)
Requires-Dist: pycryptodome (>=3.17,<4.0)
Requires-Dist: pyhumps (>=3.8.0,<4.0.0)
Requires-Dist: pytz (>=2022.7.1,<2023.0.0)
